LICENSE
README
setup.py
Graphication.egg-info/PKG-INFO
Graphication.egg-info/SOURCES.txt
Graphication.egg-info/dependency_links.txt
Graphication.egg-info/not-zip-safe
Graphication.egg-info/top_level.txt
graphication/__init__.py
graphication/barchart.py
graphication/color.py
graphication/colourer.py
graphication/css.py
graphication/curvybarchart.py
graphication/default.css
graphication/doughnut.py
graphication/empty.py
graphication/graph.py
graphication/lastfm.py
graphication/legend.py
graphication/linegraph.py
graphication/rect.py
graphication/release.py
graphication/series.py
graphication/style.py
graphication/text.py
graphication/ticks.py
graphication/verticallines.py
graphication/wavegraph.py
graphication/examples/__init__.py
graphication/examples/csv.py
graphication/examples/forcerel.py
graphication/examples/lastfm_css.css
graphication/examples/lastfm_wavegraph.py
graphication/examples/lastgraph.css
graphication/examples/random_doughnut.py
graphication/examples/random_linegraph.py
graphication/examples/random_wavegraph.py
graphication/forcerel/__init__.py
graphication/label/__init__.py
graphication/output/__init__.py
graphication/output/pdf.py
graphication/output/png.py
graphication/output/svg.py
graphication/output/svgz.py
graphication/scales/__init__.py
graphication/scales/date.py
graphication/tests/__init__.py
graphication/tests/series.py