Metadata-Version: 1.0
Name: Graphication
Version: 0.1.0
Summary: A Cairo-based graphing library
Home-page: http://aeracode.org/projects/graphication/
Author: Andrew Godwin
Author-email: graphication@aeracode.org
License: GPL
Platform: UNKNOWN
